{
  "feature_cols": [
    "home_rank",
    "away_rank",
    "home_points",
    "away_points",
    "rank_diff",
    "points_diff",
    "home_team_win_rate",
    "away_team_win_rate",
    "experience_diff"
  ],
  "median_rank": 106.0,
  "median_points": 1191.655395,
  "global_home_wr_med": 0.7142857142857143,
  "global_away_wr_med": 0.06666666666666667,
  "best_model_name": "Logistic Regression",
  "best_model_accuracy": 0.546875,
  "elite_contenders": [
    "Argentina",
    "Austria",
    "Belgium",
    "Brazil",
    "Croatia",
    "Czechoslovakia",
    "England",
    "France",
    "Germany",
    "Hungary",
    "Italy",
    "Mexico",
    "Netherlands",
    "Poland",
    "Portugal",
    "Soviet Union",
    "Spain",
    "Sweden",
    "Switzerland",
    "Turkey",
    "Uruguay",
    "West Germany",
    "Yugoslavia"
  ]
}